<?xml version="1.0"?>
<!DOCTYPE hibernate-mapping PUBLIC "-//Hibernate/Hibernate Mapping DTD 3.0//EN"
"http://hibernate.sourceforge.net/hibernate-mapping-3.0.dtd">
<!-- Generated Nov 23, 2012 11:35:36 AM by Hibernate Tools 3.2.1.GA -->
<hibernate-mapping>
    <class name="com.app.wms.hbm.bean.Goodreceive" table="goodreceive" schema="dbo" catalog="inventory">
        <id name="id" type="int">
            <column name="id" />
            <generator class="native" />
        </id>
        <property name="grnumber" type="string">
            <column name="grnumber" length="10" />
        </property>
        <property name="ponumber" type="string">
            <column name="ponumber" length="30" />
        </property>
        <property name="receiveddate" type="timestamp">
            <column name="receiveddate" length="23" />
        </property>
        <property name="createdby" type="string">
            <column name="createdby" length="30" />
        </property>
        <property name="corpid" type="string">
            <column name="corpid" length="30" />
        </property>
        <property name="whCode" type="string">
            <column name="wh_code" length="30" />
        </property>
        <property name="lotid" type="string">
            <column name="lotid" length="10" />
        </property>
        <property name="wsNo" type="string">
            <column name="wsNo" length="30" />
        </property>
        <property name="unitCost" type="java.lang.Integer">
            <column name="unitCost" />
        </property>
        <property name="amount" type="java.lang.Integer">
            <column name="amount" />
        </property>
        <property name="checkedBy" type="string">
            <column name="checkedBy" length="30" />
        </property>
        <property name="accEntry" type="string">
            <column name="accEntry" length="30" />
        </property>
        <property name="evalBy" type="string">
            <column name="evalBy" length="30" />
        </property>
        <property name="appBy" type="string">
            <column name="approvedBy" length="30" />
        </property>
        <property name="departmentName" type="string">
            <column name="department" length="30" />
        </property>
    </class>
</hibernate-mapping>
